sentry_kafka_management/__init__.py
sentry_kafka_management/brokers.py
sentry_kafka_management/cli.py
sentry_kafka_management/py.typed
sentry_kafka_management/actions/__init__.py
sentry_kafka_management/actions/brokers.py
sentry_kafka_management/actions/clusters.py
sentry_kafka_management/actions/conf.py
sentry_kafka_management/actions/topics.py
sentry_kafka_management/actions/local/__init__.py
sentry_kafka_management/actions/local/filesystem.py
sentry_kafka_management/actions/local/kafka_cli.py
sentry_kafka_management/actions/local/manage_configs.py
sentry_kafka_management/actions/local/server_properties.py
sentry_kafka_management/connectors/__init__.py
sentry_kafka_management/connectors/admin.py
sentry_kafka_management/connectors/kafkactl.py
sentry_kafka_management/scripts/__init__.py
sentry_kafka_management/scripts/brokers.py
sentry_kafka_management/scripts/clusters.py
sentry_kafka_management/scripts/config_helpers.py
sentry_kafka_management/scripts/topics.py
sentry_kafka_management/scripts/local/__init__.py
sentry_kafka_management/scripts/local/filesystem.py
sentry_kafka_management/scripts/local/manage_configs.py
sentry_kafka_management-0.0.14.dist-info/licenses/LICENSE
sentry_kafka_management-0.0.14.dist-info/METADATA
sentry_kafka_management-0.0.14.dist-info/WHEEL
sentry_kafka_management-0.0.14.dist-info/entry_points.txt
sentry_kafka_management-0.0.14.dist-info/top_level.txt
sentry_kafka_management-0.0.14.dist-info/RECORD
