Metadata-Version: 2.4
Name: sentry_kafka_management
Version: 0.0.14
Summary: Libraries used by Sentry for kafka management
Requires-Python: >=3.11
License-File: LICENSE
Requires-Dist: confluent-kafka>=2.8.0
Requires-Dist: PyYAML
Requires-Dist: click>=8.0.0
Dynamic: license-file
